{
  "generated_at": "2026-06-25T10:25:40Z",
  "generated_at_tw": "2026-06-25 10:25",
  "count": 80,
  "use_fallback": false,
  "failed_symbols": [
    "006201",
    "00928",
    "00945",
    "00858",
    "00888",
    "00931",
    "00933",
    "00942",
    "00948",
    "00699U",
    "00679B",
    "00720B",
    "00724B",
    "00725B",
    "00751B",
    "00761B",
    "00764B",
    "00772B",
    "00779B",
    "00793B",
    "00795B",
    "00796B",
    "00799B",
    "00849B",
    "00864B",
    "00869B",
    "00870B",
    "00876B",
    "00933B",
    "00696B"
  ],
  "etfs": [
    {
      "symbol": "00400A",
      "name": "國泰動能高息",
      "price": 15.0,
      "market": "TW",
      "ret_1d": 0.54,
      "ret_1w": 0.87,
      "ret_1m": 2.39,
      "ret_3m": null,
      "ret_1y": null,
      "ret_ytd": null,
      "volume": 47536845,
      "data_date": "2026-06-25"
    },
    {
      "symbol": "00401A",
      "name": "摩根台灣鑫收",
      "price": 13.79,
      "market": "TW",
      "ret_1d": -0.22,
      "ret_1w": -0.22,
      "ret_1m": 1.55,
      "ret_3m": null,
      "ret_1y": null,
      "ret_ytd": null,
      "volume": 8195788,
      "data_date": "2026-06-25"
    },
    {
      "symbol": "00403A",
      "name": "統一升級50",
      "price": 11.11,
      "market": "TW",
      "ret_1d": 0.63,
      "ret_1w": 3.35,
      "ret_1m": 4.42,
      "ret_3m": null,
      "ret_1y": null,
      "ret_ytd": null,
      "volume": 244156152,
      "data_date": "2026-06-25"
    },
    {
      "symbol": "00404A",
      "name": "聯博動能50",
      "price": 10.17,
      "market": "TW",
      "ret_1d": -0.29,
      "ret_1w": 0.79,
      "ret_1m": null,
      "ret_3m": null,
      "ret_1y": null,
      "ret_ytd": null,
      "volume": 12326118,
      "data_date": "2026-06-25"
    },
    {
      "symbol": "00405A",
      "name": "富邦台灣龍耀",
      "price": 9.43,
      "market": "TW",
      "ret_1d": 0.11,
      "ret_1w": 0.43,
      "ret_1m": -5.89,
      "ret_3m": null,
      "ret_1y": null,
      "ret_ytd": null,
      "volume": 73396841,
      "data_date": "2026-06-25"
    },
    {
      "symbol": "00406A",
      "name": "中信台灣收益",
      "price": 10.28,
      "market": "TW",
      "ret_1d": 0.69,
      "ret_1w": 1.48,
      "ret_1m": null,
      "ret_3m": null,
      "ret_1y": null,
      "ret_ytd": null,
      "volume": 23360728,
      "data_date": "2026-06-25"
    },
    {
      "symbol": "00981A",
      "name": "統一台股增長",
      "price": 31.5,
      "market": "TW",
      "ret_1d": 0.06,
      "ret_1w": 2.01,
      "ret_1m": 2.08,
      "ret_3m": 60.64,
      "ret_1y": 208.34,
      "ret_ytd": 94.01,
      "volume": 189183089,
      "data_date": "2026-06-25"
    },
    {
      "symbol": "00982A",
      "name": "凱基台灣優選",
      "price": 24.74,
      "market": "TW",
      "ret_1d": 0.49,
      "ret_1w": 2.49,
      "ret_1m": 2.83,
      "ret_3m": 57.67,
      "ret_1y": 156.93,
      "ret_ytd": 78.3,
      "volume": 26643318,
      "data_date": "2026-06-25"
    },
    {
      "symbol": "00983A",
      "name": "群益台灣核心",
      "price": 11.91,
      "market": "TW",
      "ret_1d": 1.36,
      "ret_1w": 0.25,
      "ret_1m": 2.5,
      "ret_3m": 11.31,
      "ret_1y": 19.1,
      "ret_ytd": 0.25,
      "volume": 3012094,
      "data_date": "2026-06-25"
    },
    {
      "symbol": "00984A",
      "name": "元大台灣成長",
      "price": 16.86,
      "market": "TW",
      "ret_1d": 0.66,
      "ret_1w": 1.81,
      "ret_1m": 6.31,
      "ret_3m": 40.18,
      "ret_1y": null,
      "ret_ytd": 57.31,
      "volume": 7660570,
      "data_date": "2026-06-25"
    },
    {
      "symbol": "00985A",
      "name": "永豐台灣優質",
      "price": 22.14,
      "market": "TW",
      "ret_1d": -0.27,
      "ret_1w": -0.18,
      "ret_1m": 0.45,
      "ret_3m": 38.12,
      "ret_1y": null,
      "ret_ytd": 65.1,
      "volume": 4254083,
      "data_date": "2026-06-25"
    },
    {
      "symbol": "00986A",
      "name": "富邦台灣精選",
      "price": 15.48,
      "market": "TW",
      "ret_1d": 1.64,
      "ret_1w": 1.84,
      "ret_1m": 4.88,
      "ret_3m": 30.3,
      "ret_1y": null,
      "ret_ytd": 34.26,
      "volume": 309366,
      "data_date": "2026-06-25"
    },
    {
      "symbol": "00987A",
      "name": "台新優勢成長",
      "price": 17.42,
      "market": "TW",
      "ret_1d": -0.34,
      "ret_1w": 0.35,
      "ret_1m": -3.86,
      "ret_3m": 46.76,
      "ret_1y": null,
      "ret_ytd": 72.3,
      "volume": 4343131,
      "data_date": "2026-06-25"
    },
    {
      "symbol": "00988A",
      "name": "國泰台灣芯",
      "price": 23.07,
      "market": "TW",
      "ret_1d": 2.4,
      "ret_1w": 2.44,
      "ret_1m": 5.25,
      "ret_3m": 81.94,
      "ret_1y": null,
      "ret_ytd": 128.87,
      "volume": 85562845,
      "data_date": "2026-06-25"
    },
    {
      "symbol": "00989A",
      "name": "中信台灣尖牙",
      "price": 18.15,
      "market": "TW",
      "ret_1d": 0.95,
      "ret_1w": 0.72,
      "ret_1m": 2.31,
      "ret_3m": 30.01,
      "ret_1y": null,
      "ret_ytd": 19.8,
      "volume": 3451715,
      "data_date": "2026-06-25"
    },
    {
      "symbol": "00990A",
      "name": "兆豐台灣優息",
      "price": 21.18,
      "market": "TW",
      "ret_1d": 3.27,
      "ret_1w": 2.22,
      "ret_1m": 9.29,
      "ret_3m": 76.79,
      "ret_1y": null,
      "ret_ytd": 107.44,
      "volume": 47934497,
      "data_date": "2026-06-25"
    },
    {
      "symbol": "00991A",
      "name": "日盛台灣動能",
      "price": 20.7,
      "market": "TW",
      "ret_1d": 1.52,
      "ret_1w": 3.4,
      "ret_1m": 7.09,
      "ret_3m": 68.98,
      "ret_1y": null,
      "ret_ytd": 97.71,
      "volume": 85073086,
      "data_date": "2026-06-25"
    },
    {
      "symbol": "00992A",
      "name": "群益台灣新動能",
      "price": 18.82,
      "market": "TW",
      "ret_1d": 0.43,
      "ret_1w": 0.91,
      "ret_1m": -0.53,
      "ret_3m": 46.35,
      "ret_1y": null,
      "ret_ytd": 80.44,
      "volume": 40721959,
      "data_date": "2026-06-25"
    },
    {
      "symbol": "009816",
      "name": "凱基台灣TOP50",
      "price": 15.59,
      "market": "TW",
      "ret_1d": 0.19,
      "ret_1w": 0.26,
      "ret_1m": 5.62,
      "ret_3m": 48.76,
      "ret_1y": null,
      "ret_ytd": null,
      "volume": 140348947,
      "data_date": "2026-06-25"
    },
    {
      "symbol": "0050",
      "name": "元大台灣50",
      "price": 107.2,
      "market": "TW",
      "ret_1d": 0.05,
      "ret_1w": 1.13,
      "ret_1m": 7.09,
      "ret_3m": 44.09,
      "ret_1y": 132.13,
      "ret_ytd": 65.72,
      "volume": 95851653,
      "data_date": "2026-06-25"
    },
    {
      "symbol": "0051",
      "name": "元大中型100",
      "price": 149.0,
      "market": "TW",
      "ret_1d": 0.34,
      "ret_1w": 3.26,
      "ret_1m": 6.2,
      "ret_3m": 39.06,
      "ret_1y": 106.39,
      "ret_ytd": 62.84,
      "volume": 110879,
      "data_date": "2026-06-25"
    },
    {
      "symbol": "0052",
      "name": "富邦科技",
      "price": 63.0,
      "market": "TW",
      "ret_1d": -0.08,
      "ret_1w": 1.37,
      "ret_1m": 6.33,
      "ret_3m": 46.26,
      "ret_1y": -65.0,
      "ret_ytd": 70.35,
      "volume": 22071408,
      "data_date": "2026-06-25"
    },
    {
      "symbol": "0053",
      "name": "元大電子",
      "price": 244.7,
      "market": "TW",
      "ret_1d": 0.64,
      "ret_1w": 1.12,
      "ret_1m": 4.15,
      "ret_3m": 46.75,
      "ret_1y": 147.72,
      "ret_ytd": 73.67,
      "volume": 22317,
      "data_date": "2026-06-25"
    },
    {
      "symbol": "0055",
      "name": "元大MSCI金融",
      "price": 42.71,
      "market": "TW",
      "ret_1d": 1.3,
      "ret_1w": 0.12,
      "ret_1m": 24.52,
      "ret_3m": 32.85,
      "ret_1y": 55.15,
      "ret_ytd": 33.68,
      "volume": 487576,
      "data_date": "2026-06-25"
    },
    {
      "symbol": "006208",
      "name": "富邦台50",
      "price": 248.1,
      "market": "TW",
      "ret_1d": 0.06,
      "ret_1w": 0.73,
      "ret_1m": 6.69,
      "ret_3m": 43.62,
      "ret_1y": 130.09,
      "ret_ytd": 65.29,
      "volume": 2864189,
      "data_date": "2026-06-25"
    },
    {
      "symbol": "00733",
      "name": "富邦台灣中小",
      "price": 77.2,
      "market": "TW",
      "ret_1d": 0.78,
      "ret_1w": 1.65,
      "ret_1m": 0.85,
      "ret_3m": 44.97,
      "ret_1y": 101.61,
      "ret_ytd": 69.95,
      "volume": 536061,
      "data_date": "2026-06-25"
    },
    {
      "symbol": "00850",
      "name": "元大臺灣ESG永續",
      "price": 92.2,
      "market": "TW",
      "ret_1d": 0.38,
      "ret_1w": 0.88,
      "ret_1m": 6.34,
      "ret_3m": 50.87,
      "ret_1y": 124.95,
      "ret_ytd": 70.35,
      "volume": 593077,
      "data_date": "2026-06-25"
    },
    {
      "symbol": "00905",
      "name": "FT臺灣Smart",
      "price": 28.45,
      "market": "TW",
      "ret_1d": 0.14,
      "ret_1w": 2.01,
      "ret_1m": 7.24,
      "ret_3m": 51.42,
      "ret_1y": 126.64,
      "ret_ytd": 70.32,
      "volume": 866199,
      "data_date": "2026-06-25"
    },
    {
      "symbol": "0056",
      "name": "元大高股息",
      "price": 53.2,
      "market": "TW",
      "ret_1d": 0.09,
      "ret_1w": 2.41,
      "ret_1m": 10.1,
      "ret_3m": 43.21,
      "ret_1y": 69.05,
      "ret_ytd": 51.76,
      "volume": 29041276,
      "data_date": "2026-06-25"
    },
    {
      "symbol": "00692",
      "name": "富邦公司治理",
      "price": 92.55,
      "market": "TW",
      "ret_1d": 0.22,
      "ret_1w": 0.98,
      "ret_1m": 6.07,
      "ret_3m": 41.3,
      "ret_1y": 119.5,
      "ret_ytd": 60.82,
      "volume": 652281,
      "data_date": "2026-06-25"
    },
    {
      "symbol": "00701",
      "name": "國泰股利精選30",
      "price": 40.42,
      "market": "TW",
      "ret_1d": 1.08,
      "ret_1w": 4.39,
      "ret_1m": 22.89,
      "ret_3m": 41.63,
      "ret_1y": 58.39,
      "ret_ytd": 41.64,
      "volume": 763315,
      "data_date": "2026-06-25"
    },
    {
      "symbol": "00730",
      "name": "富邦臺灣優質高息",
      "price": 29.24,
      "market": "TW",
      "ret_1d": 1.6,
      "ret_1w": 1.35,
      "ret_1m": 5.01,
      "ret_3m": 29.39,
      "ret_1y": 40.79,
      "ret_ytd": 29.71,
      "volume": 284722,
      "data_date": "2026-06-25"
    },
    {
      "symbol": "00878",
      "name": "國泰永續高股息",
      "price": 33.75,
      "market": "TW",
      "ret_1d": 0.27,
      "ret_1w": 1.44,
      "ret_1m": 13.94,
      "ret_3m": 56.57,
      "ret_1y": 75.42,
      "ret_ytd": 62.08,
      "volume": 32532018,
      "data_date": "2026-06-25"
    },
    {
      "symbol": "00900",
      "name": "富邦特選高股息30",
      "price": 19.8,
      "market": "TW",
      "ret_1d": 0.56,
      "ret_1w": 1.69,
      "ret_1m": 9.81,
      "ret_3m": 42.31,
      "ret_1y": 61.05,
      "ret_ytd": 48.1,
      "volume": 5629890,
      "data_date": "2026-06-25"
    },
    {
      "symbol": "00907",
      "name": "永豐優息存股",
      "price": 16.39,
      "market": "TW",
      "ret_1d": 0.43,
      "ret_1w": 0.82,
      "ret_1m": 11.23,
      "ret_3m": 14.35,
      "ret_1y": 15.65,
      "ret_ytd": 11.49,
      "volume": 1919414,
      "data_date": "2026-06-25"
    },
    {
      "symbol": "00915",
      "name": "凱基優選高股息30",
      "price": 33.28,
      "market": "TW",
      "ret_1d": 0.76,
      "ret_1w": 4.92,
      "ret_1m": 19.64,
      "ret_3m": 46.6,
      "ret_1y": 54.72,
      "ret_ytd": 50.43,
      "volume": 4245031,
      "data_date": "2026-06-25"
    },
    {
      "symbol": "00919",
      "name": "群益台灣精選高息",
      "price": 30.26,
      "market": "TW",
      "ret_1d": 0.17,
      "ret_1w": -0.3,
      "ret_1m": 11.99,
      "ret_3m": 39.58,
      "ret_1y": 55.89,
      "ret_ytd": 44.35,
      "volume": 71439148,
      "data_date": "2026-06-25"
    },
    {
      "symbol": "00929",
      "name": "復華台灣科技優息",
      "price": 31.86,
      "market": "TW",
      "ret_1d": 0.98,
      "ret_1w": 4.22,
      "ret_1m": 10.01,
      "ret_3m": 69.41,
      "ret_1y": 92.86,
      "ret_ytd": 82.66,
      "volume": 27145112,
      "data_date": "2026-06-25"
    },
    {
      "symbol": "00934",
      "name": "中信成長高股息",
      "price": 28.59,
      "market": "TW",
      "ret_1d": 0.95,
      "ret_1w": 0.18,
      "ret_1m": 7.78,
      "ret_3m": 38.6,
      "ret_1y": 70.2,
      "ret_ytd": 44.26,
      "volume": 2481060,
      "data_date": "2026-06-25"
    },
    {
      "symbol": "00936",
      "name": "台新永續高息中小",
      "price": 21.17,
      "market": "TW",
      "ret_1d": 2.17,
      "ret_1w": 3.32,
      "ret_1m": 5.42,
      "ret_3m": 23.2,
      "ret_1y": 49.64,
      "ret_ytd": 34.91,
      "volume": 3197377,
      "data_date": "2026-06-25"
    },
    {
      "symbol": "00940",
      "name": "元大台灣價值高息",
      "price": 12.77,
      "market": "TW",
      "ret_1d": 0.87,
      "ret_1w": 1.92,
      "ret_1m": 9.04,
      "ret_3m": 35.32,
      "ret_1y": 49.17,
      "ret_ytd": 41.69,
      "volume": 15665331,
      "data_date": "2026-06-25"
    },
    {
      "symbol": "00943",
      "name": "兆豐電子高息等權",
      "price": 22.8,
      "market": "TW",
      "ret_1d": 0.09,
      "ret_1w": 3.87,
      "ret_1m": 5.3,
      "ret_3m": 54.88,
      "ret_1y": 74.13,
      "ret_ytd": 63.26,
      "volume": 635053,
      "data_date": "2026-06-25"
    },
    {
      "symbol": "009802",
      "name": "富邦旗艦50",
      "price": 19.45,
      "market": "TW",
      "ret_1d": -0.21,
      "ret_1w": -1.62,
      "ret_1m": 0.23,
      "ret_3m": 58.69,
      "ret_1y": 110.79,
      "ret_ytd": 75.72,
      "volume": 4786020,
      "data_date": "2026-06-25"
    },
    {
      "symbol": "00830",
      "name": "國泰費城半導體",
      "price": 99.25,
      "market": "TW",
      "ret_1d": 2.64,
      "ret_1w": 3.82,
      "ret_1m": 13.95,
      "ret_3m": 82.95,
      "ret_1y": 189.52,
      "ret_ytd": 99.19,
      "volume": 7175401,
      "data_date": "2026-06-25"
    },
    {
      "symbol": "00881",
      "name": "國泰台灣5G+",
      "price": 55.35,
      "market": "TW",
      "ret_1d": 0.0,
      "ret_1w": 0.73,
      "ret_1m": 3.46,
      "ret_3m": 53.24,
      "ret_1y": 162.17,
      "ret_ytd": 83.22,
      "volume": 6965942,
      "data_date": "2026-06-25"
    },
    {
      "symbol": "00891",
      "name": "中信關鍵半導體",
      "price": 37.79,
      "market": "TW",
      "ret_1d": 0.08,
      "ret_1w": 3.11,
      "ret_1m": 7.63,
      "ret_3m": 64.1,
      "ret_1y": 157.83,
      "ret_ytd": 102.43,
      "volume": 16032291,
      "data_date": "2026-06-25"
    },
    {
      "symbol": "00893",
      "name": "國泰智能電動車",
      "price": 46.08,
      "market": "TW",
      "ret_1d": -0.04,
      "ret_1w": -1.18,
      "ret_1m": -0.58,
      "ret_3m": 40.1,
      "ret_1y": 101.84,
      "ret_ytd": 42.13,
      "volume": 916685,
      "data_date": "2026-06-25"
    },
    {
      "symbol": "00896",
      "name": "中信綠能及電動車",
      "price": 27.82,
      "market": "TW",
      "ret_1d": -0.93,
      "ret_1w": 0.83,
      "ret_1m": 3.94,
      "ret_3m": 41.89,
      "ret_1y": 106.02,
      "ret_ytd": 58.08,
      "volume": 5196052,
      "data_date": "2026-06-25"
    },
    {
      "symbol": "00902",
      "name": "中信電池及儲能",
      "price": 15.35,
      "market": "TW",
      "ret_1d": -0.9,
      "ret_1w": -3.4,
      "ret_1m": -8.19,
      "ret_3m": 11.23,
      "ret_1y": 100.92,
      "ret_ytd": 17.53,
      "volume": 898432,
      "data_date": "2026-06-25"
    },
    {
      "symbol": "00904",
      "name": "新光台灣半導體30",
      "price": 43.92,
      "market": "TW",
      "ret_1d": 0.11,
      "ret_1w": 3.34,
      "ret_1m": 6.55,
      "ret_3m": 58.1,
      "ret_1y": 182.2,
      "ret_ytd": 98.62,
      "volume": 1270481,
      "data_date": "2026-06-25"
    },
    {
      "symbol": "00913",
      "name": "兆豐台灣晶圓製造",
      "price": 55.45,
      "market": "TW",
      "ret_1d": 0.91,
      "ret_1w": 6.53,
      "ret_1m": 13.42,
      "ret_3m": 87.02,
      "ret_1y": 213.33,
      "ret_ytd": 133.76,
      "volume": 2764282,
      "data_date": "2026-06-25"
    },
    {
      "symbol": "00939",
      "name": "統一台灣高息動能",
      "price": 21.69,
      "market": "TW",
      "ret_1d": 0.7,
      "ret_1w": -0.14,
      "ret_1m": 10.04,
      "ret_3m": 42.43,
      "ret_1y": 65.88,
      "ret_ytd": 51.54,
      "volume": 2783774,
      "data_date": "2026-06-25"
    },
    {
      "symbol": "00944",
      "name": "群益半導體收益",
      "price": 22.38,
      "market": "TW",
      "ret_1d": 1.18,
      "ret_1w": 3.47,
      "ret_1m": 14.24,
      "ret_3m": 49.3,
      "ret_1y": 66.71,
      "ret_ytd": 57.02,
      "volume": 226031,
      "data_date": "2026-06-25"
    },
    {
      "symbol": "00946",
      "name": "元大AI晶片半導體",
      "price": 15.48,
      "market": "TW",
      "ret_1d": 0.98,
      "ret_1w": 2.38,
      "ret_1m": 8.51,
      "ret_3m": 57.67,
      "ret_1y": 84.11,
      "ret_ytd": 66.49,
      "volume": 5333357,
      "data_date": "2026-06-25"
    },
    {
      "symbol": "00947",
      "name": "台新臺灣IC設計動能",
      "price": 40.93,
      "market": "TW",
      "ret_1d": 0.57,
      "ret_1w": 3.1,
      "ret_1m": 8.31,
      "ret_3m": 73.85,
      "ret_1y": 214.04,
      "ret_ytd": 118.08,
      "volume": 10312695,
      "data_date": "2026-06-25"
    },
    {
      "symbol": "00910",
      "name": "第一金太空衛星",
      "price": 59.95,
      "market": "TW",
      "ret_1d": -4.39,
      "ret_1w": -10.72,
      "ret_1m": -28.84,
      "ret_3m": 3.45,
      "ret_1y": 110.06,
      "ret_ytd": 36.47,
      "volume": 5481262,
      "data_date": "2026-06-25"
    },
    {
      "symbol": "00916",
      "name": "國泰全球品牌50",
      "price": 25.13,
      "market": "TW",
      "ret_1d": 0.36,
      "ret_1w": -2.67,
      "ret_1m": -4.33,
      "ret_3m": 7.6,
      "ret_1y": 18.12,
      "ret_ytd": -1.51,
      "volume": 1264000,
      "data_date": "2026-06-25"
    },
    {
      "symbol": "00917",
      "name": "中信特選金融",
      "price": 22.3,
      "market": "TW",
      "ret_1d": -0.54,
      "ret_1w": -1.63,
      "ret_1m": 2.01,
      "ret_3m": 10.29,
      "ret_1y": 37.0,
      "ret_ytd": 12.02,
      "volume": 891739,
      "data_date": "2026-06-25"
    },
    {
      "symbol": "00918",
      "name": "大華優利高填息30",
      "price": 32.48,
      "market": "TW",
      "ret_1d": 1.25,
      "ret_1w": 3.44,
      "ret_1m": 21.3,
      "ret_3m": 53.35,
      "ret_1y": 66.98,
      "ret_ytd": 53.43,
      "volume": 61564167,
      "data_date": "2026-06-25"
    },
    {
      "symbol": "00920",
      "name": "富邦未來車",
      "price": 26.57,
      "market": "TW",
      "ret_1d": 0.91,
      "ret_1w": 1.18,
      "ret_1m": -2.71,
      "ret_3m": 27.43,
      "ret_1y": 116.19,
      "ret_ytd": 46.31,
      "volume": 413913,
      "data_date": "2026-06-25"
    },
    {
      "symbol": "00921",
      "name": "兆豐台灣核心",
      "price": 23.06,
      "market": "TW",
      "ret_1d": -0.69,
      "ret_1w": 0.17,
      "ret_1m": 5.33,
      "ret_3m": 27.92,
      "ret_1y": 43.38,
      "ret_ytd": 35.31,
      "volume": 324797,
      "data_date": "2026-06-25"
    },
    {
      "symbol": "00922",
      "name": "國泰台灣領袖50",
      "price": 41.24,
      "market": "TW",
      "ret_1d": 0.29,
      "ret_1w": 1.55,
      "ret_1m": 7.45,
      "ret_3m": 49.85,
      "ret_1y": 126.25,
      "ret_ytd": 70.28,
      "volume": 5218164,
      "data_date": "2026-06-25"
    },
    {
      "symbol": "00923",
      "name": "群益台ESG低碳50",
      "price": 43.14,
      "market": "TW",
      "ret_1d": 0.3,
      "ret_1w": 1.1,
      "ret_1m": 6.26,
      "ret_3m": 52.44,
      "ret_1y": 129.44,
      "ret_ytd": 75.14,
      "volume": 3654087,
      "data_date": "2026-06-25"
    },
    {
      "symbol": "00924",
      "name": "群益台灣工業菁英",
      "price": 31.94,
      "market": "TW",
      "ret_1d": 0.38,
      "ret_1w": -1.51,
      "ret_1m": -1.3,
      "ret_3m": 16.06,
      "ret_1y": 35.63,
      "ret_ytd": 9.23,
      "volume": 2319705,
      "data_date": "2026-06-25"
    },
    {
      "symbol": "00925",
      "name": "元大台灣高息低波",
      "price": 16.1,
      "market": "TW",
      "ret_1d": 0.0,
      "ret_1w": 2.68,
      "ret_1m": 4.55,
      "ret_3m": -6.23,
      "ret_1y": null,
      "ret_ytd": 0.0,
      "volume": 0,
      "data_date": "2025-06-10"
    },
    {
      "symbol": "00926",
      "name": "凱基台灣IA",
      "price": 24.59,
      "market": "TW",
      "ret_1d": 0.45,
      "ret_1w": -1.24,
      "ret_1m": -3.34,
      "ret_3m": 9.05,
      "ret_1y": 28.86,
      "ret_ytd": 5.49,
      "volume": 1074174,
      "data_date": "2026-06-25"
    },
    {
      "symbol": "00927",
      "name": "永豐ESG低碳高息",
      "price": 42.36,
      "market": "TW",
      "ret_1d": 0.5,
      "ret_1w": 5.58,
      "ret_1m": 7.35,
      "ret_3m": 82.35,
      "ret_1y": 174.0,
      "ret_ytd": 108.22,
      "volume": 16899908,
      "data_date": "2026-06-25"
    },
    {
      "symbol": "00930",
      "name": "永豐台灣ESG優質",
      "price": 25.77,
      "market": "TW",
      "ret_1d": 0.04,
      "ret_1w": 2.87,
      "ret_1m": 10.89,
      "ret_3m": 52.29,
      "ret_1y": 59.4,
      "ret_ytd": 53.17,
      "volume": 866992,
      "data_date": "2026-06-25"
    },
    {
      "symbol": "00932",
      "name": "兆豐永續高息等權",
      "price": 17.64,
      "market": "TW",
      "ret_1d": 0.17,
      "ret_1w": 0.57,
      "ret_1m": 5.95,
      "ret_3m": 23.75,
      "ret_1y": 30.4,
      "ret_ytd": 27.69,
      "volume": 1115146,
      "data_date": "2026-06-25"
    },
    {
      "symbol": "00935",
      "name": "野村臺灣創新科技50",
      "price": 62.0,
      "market": "TW",
      "ret_1d": 0.16,
      "ret_1w": 1.06,
      "ret_1m": 3.33,
      "ret_3m": 69.17,
      "ret_1y": 211.95,
      "ret_ytd": 112.19,
      "volume": 10807155,
      "data_date": "2026-06-25"
    },
    {
      "symbol": "00938",
      "name": "永豐ESG高息成長",
      "price": 24.6,
      "market": "TW",
      "ret_1d": 0.78,
      "ret_1w": 0.53,
      "ret_1m": 15.22,
      "ret_3m": 36.38,
      "ret_1y": 77.26,
      "ret_ytd": 44.02,
      "volume": 658510,
      "data_date": "2026-06-25"
    },
    {
      "symbol": "00646",
      "name": "元大S&P500",
      "price": 74.15,
      "market": "OTHER",
      "ret_1d": 0.54,
      "ret_1w": -0.67,
      "ret_1m": -0.4,
      "ret_3m": 12.69,
      "ret_1y": 33.0,
      "ret_ytd": 9.2,
      "volume": 1739795,
      "data_date": "2026-06-25"
    },
    {
      "symbol": "00757",
      "name": "統一FANG+",
      "price": 126.45,
      "market": "OTHER",
      "ret_1d": 0.76,
      "ret_1w": -2.24,
      "ret_1m": -2.01,
      "ret_3m": 17.25,
      "ret_1y": 26.45,
      "ret_ytd": 7.02,
      "volume": 1488512,
      "data_date": "2026-06-25"
    },
    {
      "symbol": "00662",
      "name": "富邦NASDAQ",
      "price": 122.0,
      "market": "OTHER",
      "ret_1d": 1.29,
      "ret_1w": -0.33,
      "ret_1m": 1.46,
      "ret_3m": 23.73,
      "ret_1y": 46.55,
      "ret_ytd": 18.85,
      "volume": 8468498,
      "data_date": "2026-06-25"
    },
    {
      "symbol": "00670L",
      "name": "富邦NASDAQ正2",
      "price": 210.0,
      "market": "OTHER",
      "ret_1d": 1.89,
      "ret_1w": -2.82,
      "ret_1m": -0.83,
      "ret_3m": 48.73,
      "ret_1y": 64.51,
      "ret_ytd": 28.95,
      "volume": 956407,
      "data_date": "2026-06-25"
    },
    {
      "symbol": "00631L",
      "name": "元大台灣50正2",
      "price": 38.16,
      "market": "OTHER",
      "ret_1d": 0.21,
      "ret_1w": 1.73,
      "ret_1m": 10.93,
      "ret_3m": 89.44,
      "ret_1y": 301.68,
      "ret_ytd": 131.34,
      "volume": 249588960,
      "data_date": "2026-06-25"
    },
    {
      "symbol": "00632R",
      "name": "元大台灣50反1",
      "price": 10.04,
      "market": "OTHER",
      "ret_1d": 0.0,
      "ret_1w": -1.18,
      "ret_1m": -6.34,
      "ret_3m": -30.81,
      "ret_1y": -55.0,
      "ret_ytd": -39.0,
      "volume": 116226129,
      "data_date": "2026-06-25"
    },
    {
      "symbol": "006205",
      "name": "富邦上証180",
      "price": 42.04,
      "market": "OTHER",
      "ret_1d": 1.4,
      "ret_1w": 2.36,
      "ret_1m": 1.94,
      "ret_3m": 9.08,
      "ret_1y": 36.98,
      "ret_ytd": 6.62,
      "volume": 1721538,
      "data_date": "2026-06-25"
    },
    {
      "symbol": "00635U",
      "name": "元大S&P黃金",
      "price": 41.66,
      "market": "OTHER",
      "ret_1d": -1.86,
      "ret_1w": -7.79,
      "ret_1m": -12.02,
      "ret_3m": -9.42,
      "ret_1y": 12.53,
      "ret_ytd": -10.29,
      "volume": 6356914,
      "data_date": "2026-06-25"
    },
    {
      "symbol": "00682U",
      "name": "富邦石油",
      "price": 20.79,
      "market": "OTHER",
      "ret_1d": 0.63,
      "ret_1w": 1.86,
      "ret_1m": 1.96,
      "ret_3m": 1.71,
      "ret_1y": 3.13,
      "ret_ytd": 3.13,
      "volume": 6148,
      "data_date": "2026-06-25"
    }
  ]
}